amz_extractor/__init__.py
amz_extractor/listing_extractor.py
amz_extractor/review_extractor.py
amz_extractor-1.1.5.dist-info/METADATA
amz_extractor-1.1.5.dist-info/WHEEL
amz_extractor-1.1.5.dist-info/top_level.txt
amz_extractor-1.1.5.dist-info/RECORD
