Metadata-Version: 2.4
Name: amz_extractor
Version: 1.1.5
Summary: 提取亚马逊详情页和评论信息
Author: lonely
Requires-Dist: dateparser>=1.1.4
Requires-Dist: pyquery>=1.4.3
Dynamic: author
Dynamic: requires-dist
Dynamic: summary
